simulate.py
simulatedistribution.py
simulatedistributions.py
simulatedistribution-1.2.0.dist-info/DESCRIPTION.rst
simulatedistribution-1.2.0.dist-info/METADATA
simulatedistribution-1.2.0.dist-info/RECORD
simulatedistribution-1.2.0.dist-info/WHEEL
simulatedistribution-1.2.0.dist-info/metadata.json
simulatedistribution-1.2.0.dist-info/top_level.txt
