Metadata-Version: 2.0
Name: simulatedistribution
Version: 1.2.0
Summary: A function that generates samples from normal, Poisson or binomial distributions
Home-page: UNKNOWN
Author: Christine Turner
Author-email: UNKNOWN
License: UNKNOWN
Platform: UNKNOWN
Requires-Dist: numpy
